<?xml version="1.0" encoding="UTF-8"?>
<LanguageData>
  
  <!-- EN: monosword -->
  <MeleeWeapon_MonoSword.label>Nano-espada</MeleeWeapon_MonoSword.label>
  <!-- EN: A crystal-metallic longsword infused with mechanites that maintain a mono-molecular cutting edge. It cuts through even thick armor with ease, and its light weight permits fast attacks. -->
  <MeleeWeapon_MonoSword.description>Una espada larga con un núcleo de metal de cristal y nanitos integrados que esperan el filo monomolecular. Corta incluso la armadura más gruesa con facilidad y sigue siendo muy ligera, lo que permite ataques rápidos.</MeleeWeapon_MonoSword.description>
  <!-- EN: handle -->
  <MeleeWeapon_MonoSword.tools.handle.label>Manejar</MeleeWeapon_MonoSword.tools.handle.label>
  <!-- EN: point -->
  <MeleeWeapon_MonoSword.tools.point.label>Arriba</MeleeWeapon_MonoSword.tools.point.label>
  <!-- EN: edge -->
  <MeleeWeapon_MonoSword.tools.edge.label>Filo</MeleeWeapon_MonoSword.tools.edge.label>
  
  <!-- EN: plasmasword -->
  <MeleeWeapon_PlasmaSword.label>Espada de plasma</MeleeWeapon_PlasmaSword.label>
  <!-- EN: A metal-cored sword with a cutting edge. Plasma is wrapped around the core, held in place by an energy field. Targets are both sliced by the metal core, as well as burned or ignited by the plasma sheath. -->
  <MeleeWeapon_PlasmaSword.description>Una espada con un núcleo de metal y una cuchilla afilada. El plasma se envuelve alrededor del núcleo y se mantiene en su lugar con la ayuda de campos magnéticos. Los objetivos son cortados por la cuchilla y prendidos o quemados por la envoltura de plasma.</MeleeWeapon_PlasmaSword.description>
  <!-- EN: handle -->
  <MeleeWeapon_PlasmaSword.tools.handle.label>Manejar</MeleeWeapon_PlasmaSword.tools.handle.label>
  <!-- EN: point -->
  <MeleeWeapon_PlasmaSword.tools.point.label>Arriba</MeleeWeapon_PlasmaSword.tools.point.label>
  <!-- EN: edge -->
  <MeleeWeapon_PlasmaSword.tools.edge.label>Filo</MeleeWeapon_PlasmaSword.tools.edge.label>
  
  <!-- EN: zeushammer -->
  <MeleeWeapon_Zeushammer.label>Martillo de Zeus</MeleeWeapon_Zeushammer.label>
  <!-- EN: A warhammer with an embedded EMP capacitor. Upon impact, it blasts the target with an EMP burst in addition to the physical damage. -->
  <MeleeWeapon_Zeushammer.description>Un martillo de guerra con un condensador EMP incorporado. En el impacto, el enemigo es golpeado por un pulso electromagnético además del daño físico.</MeleeWeapon_Zeushammer.description>
  <!-- EN: handle -->
  <MeleeWeapon_Zeushammer.tools.handle.label>Manejar</MeleeWeapon_Zeushammer.tools.handle.label>
  <!-- EN: head -->
  <MeleeWeapon_Zeushammer.tools.head.label>Cabeza</MeleeWeapon_Zeushammer.tools.head.label>
  
</LanguageData>