<?xml version="1.0" encoding="utf-8" ?>
<LanguageData>
    
    <RecruitPrisonerChance.label>Posibilidades de reclutar prisioneros</RecruitPrisonerChance.label>
    <RecruitPrisonerChance.description>Valor base que representa las posibilidades de que esta persona consiga reclutar a un prisionero.</RecruitPrisonerChance.description>
    
    <SocialImpact.label>efectividad de charla social</SocialImpact.label>
    <SocialImpact.description>Este valor representa la efectividad de la interacción social cuando esta persona interactua socialmente con otra.</SocialImpact.description>
    
    <GiftImpact.label>efectividad de regalo diplomático</GiftImpact.label>
    <GiftImpact.description>Este multiplicador es aplicado al impacto sobre las relaciones con la facción cuando esta persona realiza regalos a otra facción</GiftImpact.description>
    
    <TradePriceImprovement.label>mejoría sobre precio de comercio</TradePriceImprovement.label>
    <TradePriceImprovement.description>Los precios de compra y venta son mejorados por este porcentaje cuando esta persona es quén negocia los precios.</TradePriceImprovement.description>
    
</LanguageData>
