<?xml version="1.0" encoding="UTF-8"?>
<LanguageData>
  
  <!-- EN: heatstroke -->
  <Heatstroke.label>golpe de calor</Heatstroke.label>
  <!-- EN: A generalized disruption to body functioning caused by excessive exposure to heat and sun. The victim becomes dizzy, weak, and confused. Recovery is quick once in a cool area, but if heat exposure continues, heat stroke gets worse until death. -->
  <Heatstroke.description>Una alteración generalizada del funcionamiento del cuerpo por exposición excesiva al calor y el sol. La víctima se siente débil, mareada y confusa. La recuperación es rápida cuando se está en un lugar fresco, pero si la exposición al calor continúa, el golpe de calor empeora hasta ser fatal.</Heatstroke.description>
  <!-- EN: initial -->
  <Heatstroke.stages.initial-0.label>fase inicial</Heatstroke.stages.initial-0.label>
  <!-- EN: initial -->
  <Heatstroke.stages.initial-1.label>ligero</Heatstroke.stages.initial-1.label>
  <!-- EN: minor -->
  <Heatstroke.stages.minor.label>moderado</Heatstroke.stages.minor.label>
  <!-- EN: serious -->
  <Heatstroke.stages.serious.label>grave</Heatstroke.stages.serious.label>
  <!-- EN: extreme -->
  <Heatstroke.stages.extreme.label>extremo</Heatstroke.stages.extreme.label>
  
  <!-- EN: hypothermia -->
  <Hypothermia.label>hipotermia</Hypothermia.label>
  <!-- EN: Dangerously low core body temperature. Unless re-warmed, hypothermia gets worse and ends in death. Recovery is quick once the victim is re-warmed. Avoid hypothermia by wearing warm clothes in cold environments. -->
  <Hypothermia.description>Temperatura del núcleo del cuerpo peligrosamente baja. A menos que la víctima entre en calor, la hipotermia empeora hasta terminar en muerte. La recuperación es rápida una vez la víctima vuelve a entrar en calor. Evita la hipotermia llevando ropas de abrigo en atmósferas frías.</Hypothermia.description>
  <!-- EN: shivering -->
  <Hypothermia.stages.shivering-0.label>tiritando</Hypothermia.stages.shivering-0.label>
  <!-- EN: shivering -->
  <Hypothermia.stages.shivering-1.label>tiritando</Hypothermia.stages.shivering-1.label>
  <!-- EN: minor -->
  <Hypothermia.stages.minor.label>moderada</Hypothermia.stages.minor.label>
  <!-- EN: serious -->
  <Hypothermia.stages.serious.label>grave</Hypothermia.stages.serious.label>
  <!-- EN: extreme -->
  <Hypothermia.stages.extreme.label>extrema</Hypothermia.stages.extreme.label>
  
  <!-- EN: hypothermic slowdown -->
  <HypothermicSlowdown.label>relentización hipotérmica</HypothermicSlowdown.label>
  <!-- EN: A special biological state used by some creatures to survive extreme cold. Instead of trying to stay warm, the creature's body chemistry adapts to prevent internal freezing despite very low temperature. Bodily functions are slowed and capacities are reduced, but the cold does no permanent damage. Some biologists call it a wakeful form of hibernation. -->
  <HypothermicSlowdown.description>Un estado biológico especial que algunas criaturas utilizan para sobrevivir al frío extremo. En lugar de permanecer caliente, la química del cuerpo de la criatura se adapta para prevenir el congelamiento interno a pesar de la baja temperatura. Las funciones corporales se ralentizan y las capacidades se reducen, pero el frío no causa un daño permanente. Algunos biólogos se refieren a ello como una forma despierta de hibernar.</HypothermicSlowdown.description>
  <!-- EN: minor -->
  <HypothermicSlowdown.stages.minor-0.label>fase inicial</HypothermicSlowdown.stages.minor-0.label>
  <!-- EN: minor -->
  <HypothermicSlowdown.stages.minor-1.label>ligera</HypothermicSlowdown.stages.minor-1.label>
  <!-- EN: moderate -->
  <HypothermicSlowdown.stages.moderate.label>moderada</HypothermicSlowdown.stages.moderate.label>
  <!-- EN: serious -->
  <HypothermicSlowdown.stages.serious.label>grave</HypothermicSlowdown.stages.serious.label>
  <!-- EN: extreme -->
  <HypothermicSlowdown.stages.extreme.label>extrema</HypothermicSlowdown.stages.extreme.label>
  
</LanguageData>