<?xml version="1.0" encoding="UTF-8"?>
<LanguageData>
  
  <!-- EN: absorbed xenogerm -->
  <AbsorbedXenogerm.label>xenogermen absorbido</AbsorbedXenogerm.label>
  
  <!-- EN: extracted hemogen from member -->
  <ExtractedHemogenPack.label>hemógeno extraído de un colono</ExtractedHemogenPack.label>
  
  <!-- EN: polluted base -->
  <PollutedBase.label>base contaminada</PollutedBase.label>
  
  <!-- EN: polluted nearby site -->
  <PollutedNearbySite.label>sitio cercano contaminado</PollutedNearbySite.label>
  
  <!-- EN: toxic waste dumping -->
  <ToxicWasteDumping.label>vertido de residuos tóxicos</ToxicWasteDumping.label>
  
</LanguageData>