<?xml version="1.0" encoding="UTF-8"?>
<LanguageData>
  
  <!-- EN: ancient cryptosleep pod -->
  <AncientCryptosleepPod.label>cápsula de criptosueño antigua</AncientCryptosleepPod.label>
  <!-- EN: A single-use pod for preserving one person in a state of suspended animation. Unlike cryptosleep caskets, cryptosleep pods can only be used once. -->
  <AncientCryptosleepPod.description>Una cápsula de un solo uso para preservar a una persona en un estado de animación suspendida. En diferencia a los ataúdes de criptosueño, las capsulas solo podrán usarse una vez.</AncientCryptosleepPod.description>
  
  <!-- EN: ancient unstable fuel node -->
  <AncientFuelNode.label>nodo de combustible inestable antiguo</AncientFuelNode.label>
  <!-- EN: An ancient, unstable fuel node once used to charge machines with fuel. It has become unstable over the years due to lack of maintenance. -->
  <AncientFuelNode.description>Un antiguo e inestable nodo de combustible que en su día se utilizaba para cargar las máquinas con combustible. Se volvió inestable con el paso de los años debido a la falta de mantenimiento.</AncientFuelNode.description>
  
  <!-- EN: hermetic crate -->
  <AncientHermeticCrate.label>caja hermética</AncientHermeticCrate.label>
  <!-- EN: A self-powered hermetically-sealed crate for preserving valuable items. These can preserve their contents for a long time. -->
  <AncientHermeticCrate.description>Una caja hermética autoalimentada para conservar objetos de valor. Pueden conservar su contenido durante mucho tiempo.</AncientHermeticCrate.description>
  
</LanguageData>