<?xml version="1.0" encoding="UTF-8"?>
<LanguageData>
  
  <!-- EN: gestate agrihand -->
  <Agrihand.label>gestar mano agrícola</Agrihand.label>
  <!-- EN: Gestate an agrihand mechanoid. -->
  <Agrihand.description>Gesta una mano agrícola mecanoide.</Agrihand.description>
  <!-- EN: Gestating mech. -->
  <Agrihand.jobString>Gestando meca.</Agrihand.jobString>
  
  <!-- EN: gestate cleansweeper -->
  <Cleansweeper.label>gestar limpiador</Cleansweeper.label>
  <!-- EN: Gestate a cleansweeper mechanoid. -->
  <Cleansweeper.description>Gesta un limpiador mecanoide.</Cleansweeper.description>
  <!-- EN: Gestating mech. -->
  <Cleansweeper.jobString>Gestando meca.</Cleansweeper.jobString>
  
  <!-- EN: gestate constructoid -->
  <Constructoid.label>gestar constructoide</Constructoid.label>
  <!-- EN: Gestate a constructoid mechanoid. -->
  <Constructoid.description>Gesta un constructor mecanoide.</Constructoid.description>
  <!-- EN: Gestating mech. -->
  <Constructoid.jobString>Gestando meca.</Constructoid.jobString>
  
  <!-- EN: gestate fabricor -->
  <Fabricor.label>gestar fabricador</Fabricor.label>
  <!-- EN: Gestate a fabricor mechanoid. -->
  <Fabricor.description>Gesta un fabricador mecanoide.</Fabricor.description>
  <!-- EN: Gestating mech. -->
  <Fabricor.jobString>Gestando meca.</Fabricor.jobString>
  
  <!-- EN: gestate lifter -->
  <Lifter.label>gestar levantador</Lifter.label>
  <!-- EN: Gestate a lifter mechanoid. -->
  <Lifter.description>Gesta un levantador mecanoide.</Lifter.description>
  <!-- EN: Gestating mech. -->
  <Lifter.jobString>Gestando meca.</Lifter.jobString>
  
  <!-- EN: gestate militor -->
  <Militor.label>gestar militor</Militor.label>
  <!-- EN: Gestate a militor mechanoid. -->
  <Militor.description>Gesta un militor mecanoide.</Militor.description>
  <!-- EN: Gestating mech. -->
  <Militor.jobString>Gestando meca.</Militor.jobString>
  
  <!-- EN: gestate paramedic -->
  <Paramedic.label>gestar paramédico</Paramedic.label>
  <!-- EN: Gestate a paramedic mechanoid. -->
  <Paramedic.description>Gesta un paramédico mecanoide.</Paramedic.description>
  <!-- EN: Gestating mech. -->
  <Paramedic.jobString>Gestando meca.</Paramedic.jobString>
  
</LanguageData>