<?xml version="1.0" encoding="UTF-8"?>
<LanguageData>
  
  <!-- UNUSED -->
  <MessageSiegersAssaulting>Los {0} de {1} que te asediaban, están asaltando la colonia.</MessageSiegersAssaulting>
  <MessageRaidersBeginningAssault>Los {0} de {1} están comenzando su asalto.</MessageRaidersBeginningAssault>
  <MessageRaidersDetectedEarlyAssault>Los {0} de {1} te han detectado y han adelantado su asalto.</MessageRaidersDetectedEarlyAssault>
  <MessageRaidersKidnapping>Los {0} de {1} han decidido raptar a quien puedan e irse.</MessageRaidersKidnapping>
  <MessageRaidersStealing>Los {0} de {1} han decidido robar lo que puedan e irse.</MessageRaidersStealing>
  <MessageCaravanDetectedRaidArrived>Los {0} de {1} han llegado al area de tu caravana y están atacando. Hay más en camino y llegarán en {2}</MessageCaravanDetectedRaidArrived>
  <MessageRaidersLeaving>Los {0} de {1} se están yendo.</MessageRaidersLeaving>
  <MessageRaidersGivenUpLeaving>Los {0} de {1} se han dado por vencidos y ya se van.</MessageRaidersGivenUpLeaving>
  <MessageRaidersSatisfiedLeaving>Los {0} de {1} están satisfechos con el daño que te han causado y ya se van.</MessageRaidersSatisfiedLeaving>
  <MessageFightersFleeing>Los {0} de {1} están huyendo.</MessageFightersFleeing>
  <MessageFriendlyFightersLeaving>Los {0} amistosos de {1} ya se van.</MessageFriendlyFightersLeaving>
  <MessageVisitorsTakingWounded>Los {0} de {1} se llevan a un huésped herido.</MessageVisitorsTakingWounded>
  <MessageVisitorsTrappedLeaving>Los {0} de {1} han quedado atrapados y están excavando para escapar.</MessageVisitorsTrappedLeaving>
  <MessageVisitorsDangerousTemperature>Los {0} de {1} estan abandonando el mapa a causa de las peligrosas temperaturas.</MessageVisitorsDangerousTemperature>
  <MessageWornApparelDeterioratedAway>El/la {0} que vestía {1_nameFull} se ha deteriorado por completo.</MessageWornApparelDeterioratedAway>
  <MessageDeterioratedAway>{0} se ha deteriorado en el almacén.</MessageDeterioratedAway>
  <MessageSeasonBegun>Ahora es {0}.</MessageSeasonBegun>
  <MessageShipHasLeftCommsRange>{0} ha salido del alcance de las comunicaciones.</MessageShipHasLeftCommsRange>
  <MessageNeedBeaconToTradeWithShip>Necesitas una baliza de comercio orbital para comerciar con una nave.</MessageNeedBeaconToTradeWithShip>
  <MessageNeedRoyalTitleToCallWithShip>La persona que contacte debe poseer el título de {0} o mayor.</MessageNeedRoyalTitleToCallWithShip>
  <MessageConditionCauserDespawned>{0} ha sido destruido(a).</MessageConditionCauserDespawned>
  <MessageBillComplete>Proyecto completado: {0}.</MessageBillComplete>
  <MessageFullyHealed>{1_label} ha sanado por completo.</MessageFullyHealed>
  <MessagePrisonerIsEscaping>El prisonero {1_labelShort} está escapando.</MessagePrisonerIsEscaping>
  <MessageOutOfNearbyShellsFor>{PAWN_labelShort} no ha encontrado munición sin reservar para el/la {GUN_label}.</MessageOutOfNearbyShellsFor>
  <MessageOutOfNearbyFuelFor>{PAWN_labelShort} no ha encontrado {FUEL} sin reservar para {GUN_label}.</MessageOutOfNearbyFuelFor>
  <MessageAnimalsGoPsychoHunted>Advertencia: {ANIMAL_kindBasePlural} tiene una probabilidad de {1} de atacar al ser herido al alcance máximo del rifle. La probabilidad es mayor si se está más cerca, y menor con un cazador sigiloso.</MessageAnimalsGoPsychoHunted>
  <MessageAnimalManhuntsOnTameFailed>Advertencia: {ANIMAL_kindBasePlural} podría atacar si el intento de domesticación falla (probabilidad de {1}).</MessageAnimalManhuntsOnTameFailed>
  <MessageInsectTameDesignated>Solo aquellos con el rasgo simpatía por los insectos puede domesticar {INSECT_indefinite}.</MessageInsectTameDesignated>
  <MessageInsectsHostileOnTaming>El {PAWN_labelShort} es hostil y atacará mientras tus colonos intentan domesticarlo.</MessageInsectsHostileOnTaming>
  <LetterLabelMessageRecruitSuccess>Nuevo recluta</LetterLabelMessageRecruitSuccess>
  <MessageRecruitSuccess>{RECRUITER_nameFull} ha reclutado con éxito a {RECRUITEE_nameFull} (probabilidad de {2}).</MessageRecruitSuccess>
  <MessageTameSuccess>{RECRUITER_labelShort} ha domesticado con éxito un(a) {1} (probabilidad de {2}).</MessageTameSuccess>
  <MessageTameAndNameSuccess>{RECRUITER_labelShort} ha domesticado con éxito un(a) {1} (probabilidad de {2}) y {RECRUITEE_objective} ha llamado {RECRUITEE_nameFull}.</MessageTameAndNameSuccess>
  <MessageTameNoSuitablePens>No hay un corral adecuado para {ANIMAL_labelShort}. Eventualmente se irá.</MessageTameNoSuitablePens>
  <MessageRecruitJoinOfferAccepted>{RECRUITEE} se ha unido a tu colonia.</MessageRecruitJoinOfferAccepted>
  <MessageColonyCannotAfford>La colonia no puede costear esto.</MessageColonyCannotAfford>
  <MessageColonyNotEnoughSilver>No tienes suficiente plata almacenada para comerciar.</MessageColonyNotEnoughSilver>
  <MessageCriticalAlert>Alerta crítica: {0}</MessageCriticalAlert>
  <MessageMustDesignateHarvestable>Debes designar plantas cosechables suficientemente maduras.</MessageMustDesignateHarvestable>
  <MessageMustDesignateHarvestableWood>Debes designar árboles suficientemente maduros.</MessageMustDesignateHarvestableWood>
  <MessageMustDesignatePlants>Debes designar plantas.</MessageMustDesignatePlants>
  <MessageMustDesignateHaulable>Debes designar objetos móviles. Algunos objetos siempre son móviles y no pueden ser designados.</MessageMustDesignateHaulable>
  <MessageMustDesignateMineable>Debes designar paredes de roca minable.</MessageMustDesignateMineable>
  <MessageMustDesignateHuntable>Debes designar animales cazables.</MessageMustDesignateHuntable>
  <MessageMustDesignateTameable>Debes designar animales domesticables.</MessageMustDesignateTameable>
  <MessageMustDesignateClaimable>Debes designar estructuras abandonadas.</MessageMustDesignateClaimable>
  <MessageMustDesignateDeconstructibleMechCluster>Debes derrotar a la agrupación mecanoide antes de poder deconstruirlo.</MessageMustDesignateDeconstructibleMechCluster>
  <MessageMustDesignateSmoothableSurface>Debe designar formaciones de piedra naturales.</MessageMustDesignateSmoothableSurface>
  <MessageNothingCanRemoveThickRoofs>Nada puede eliminar techos tan gruesos.</MessageNothingCanRemoveThickRoofs>
  <MessageAlreadyInStorage>Ya se encuentra en un almacén, y será llevado a un almacén de alta prioridad de ser necesario.</MessageAlreadyInStorage>
  <MessageMustDesignateStrippable>Debes designar cadáveres o personajes incapacitados con vestimentas.</MessageMustDesignateStrippable>
  <MessageMustDesignateSlaughterable>Debes designar un animal doméstico que pertenezca a la colonia.</MessageMustDesignateSlaughterable>
  <MessageMustDesignateOpenable>Debes designar tumbas o contenedores llenos.</MessageMustDesignateOpenable>
  <MessageMustDesignateForbiddable>Debe designar objetos no prohibidos.</MessageMustDesignateForbiddable>
  <MessageMustDesignateUnforbiddable>Debe designar objetos prohibidos.</MessageMustDesignateUnforbiddable>
  <MessageRefusedArrest>¡{1_labelShort} se niega a ser arrestado(a)!</MessageRefusedArrest>
  <MessageNoMedicalBeds>No hay camas médicas disponibles.</MessageNoMedicalBeds>
  <MessageNoAnimalBeds>No hay camas para animales disponibles.</MessageNoAnimalBeds>
  <MessageTooLowMedCare>La operación requiere un nivel de medicina de {0} o mayor, pero el nivel de {PAWN_labelShort} es "{2}".</MessageTooLowMedCare>
  <PawnDiedBecauseOf>{PAWN_labelShort} ha muerto. Causa: {1}.</PawnDiedBecauseOf>
  <PawnDied>{1_labelShort} ha muerto.</PawnDied>
  <MessageNoLongerDowned>{1_label} ya puede caminar.</MessageNoLongerDowned>
  <MessageInvoluntarySleep>{1_labelShort} ha colapsado debido al agotamiento extremo.</MessageInvoluntarySleep>
  <MessageMedicalOperationWillAngerFaction>Esta operación va a enfadar a {0}.</MessageMedicalOperationWillAngerFaction>
  <MessageAnimalIsPregnant>¡{PAWN_nameDef} está embarazada!</MessageAnimalIsPregnant>
  <MessageMiscarriedStarvation>{0} ha sufrido un aborto por inanición.</MessageMiscarriedStarvation>
  <MessageMiscarriedPoorHealth>{0} ha sufrido un aborto por su mala salud.</MessageMiscarriedPoorHealth>
  <MessageGaveBirth>{0} ha dado a luz.</MessageGaveBirth>
  <MessagePsylinkNoSensitivity>{PAWN_labelShort} no podrá usar su poder psíquico mientras su sensibilidad psíquica sea cero.</MessagePsylinkNoSensitivity>
  <MessageLostImplantLevelFromHediff>{PAWN_labelShort} ha perdido un implante de nivel {1} a causa de {2}.</MessageLostImplantLevelFromHediff>
  <MessageReceivedBrainDamageFromHediff>{PAWN_labelShort} ha sufrido {1} puntos de daño cerebral a causa de {2}.</MessageReceivedBrainDamageFromHediff>
  <MessageWentOverPsychicEntropyLimit>{PAWN_labelShort} ha sobrepasado el límite de seguridad de entropía psíquica.</MessageWentOverPsychicEntropyLimit>
  <MessageNoHandlerSkilledEnough>Ningún colono puede domesticar este(a) {ANIMAL_kindBase} (requiere nivel {1} en {2} y el más capacitado es {HANDLER_labelShort}, con nivel {4}).</MessageNoHandlerSkilledEnough>
  <MessageEatenByPredator>{EATEN_labelShort} ha sido devorado(a) por {PREDATOR}.</MessageEatenByPredator>
  <MessageAttackedByPredator>¡{PREY_labelShort} está siendo atacado(a) por {PREDATOR}!</MessageAttackedByPredator>
  <MessageRoamerLeaving>¡{PAWN_labelShort} ha empezado a deambular! {PAWN_pronoun} saldrá del mapa a no ser que un cuidador de animales enganche a {PAWN_objective} de vuelta al corral.</MessageRoamerLeaving>
  <MessageHiveReproduced>Una colmena insectoide se ha reproducido.</MessageHiveReproduced>
  <MessageTraderCaravanLeaving>La caravana de {0} ya se va.</MessageTraderCaravanLeaving>
  <MessageCantSelectDeadPawn>{1_labelShort} está muerto(a).</MessageCantSelectDeadPawn>
  <MessageCantSelectOffMapPawn>{1_labelShort} ha salido del mapa.</MessageCantSelectOffMapPawn>
  <MessageSocialFight>{PAWN1_labelShort} ha comenzado una pelea con {PAWN2_labelShort}.</MessageSocialFight>
  <MessageNewMarriageCeremony>Los colonos se están reuniendo para celebrar el matrimonio de {PAWN1_labelShort} y {PAWN2_labelShort}.</MessageNewMarriageCeremony>
  <MessageMarriageCeremonyStarts>¡{PAWN1_labelShort} y {PAWN2_labelShort} han comenzado su ceremonia de matrimonio!</MessageMarriageCeremonyStarts>
  <MessageMarriageCeremonyCalledOff>La ceremonia de matrimonio de {PAWN1_labelShort} y {PAWN2_labelShort} se ha suspendido.</MessageMarriageCeremonyCalledOff>
  <MessageNewlyMarried>{PAWN1_labelShort} y {PAWN2_labelShort} se han casado. Los colonos están celebrando el feliz acontecimiento.</MessageNewlyMarried>
  <MessageMarriageCeremonyAfterPartyFinished>La ceremonia de matrimonio de {PAWN1_labelShort} y {PAWN2_labelShort} ha terminado.</MessageMarriageCeremonyAfterPartyFinished>
  <MessageNewBondRelation>{HUMAN_labelShort} y {ANIMAL_labelShort} han creado un vínculo.</MessageNewBondRelation>
  <MessageNewBondRelationNewName>{HUMAN_labelShort} y {1} han creado un vínculo. {HUMAN_labelShort} ha nombrado a {ANIMAL_objective} {ANIMAL_nameFull}.</MessageNewBondRelationNewName>
  <MessageBondedAnimalMentalBreak>{ANIMAL} ha sufrido un colapso mental debido a la muerte de {HUMAN_labelShort}.</MessageBondedAnimalMentalBreak>
  <MessageNamedBondedAnimalMentalBreak>El/la {ANIMAL_kindIndef} llamado(a) {ANIMAL_label} ha sufrido un colapso mental debido a la muerte de {HUMAN_labelShort}.</MessageNamedBondedAnimalMentalBreak>
  <MessageBondedAnimalsMentalBreak>{0} animales han sufrido un colapso mental debido a la muerte de {HUMAN_labelShort}.</MessageBondedAnimalsMentalBreak>
  <MessageSuccessfullyRemovedHediff>{SURGEON_labelShort} he extirpado con éxito el {HEDIFF} de {PATIENT_labelShort}.</MessageSuccessfullyRemovedHediff>
  <MessageShipChunkDrop>Unos pedazos de nave espacial han caído cerca de aquí. Puedes desmontarlos para reciclar sus recursos.</MessageShipChunkDrop>
  <MessageCannotSellItemsReason>Algunos objetos no pueden intercambiarse porque: </MessageCannotSellItemsReason>
  <MessageConstructionFailed>{WORKER_labelShort} ha fallado al construir el/la {0}. Se han desperdiciado algunos recursos.</MessageConstructionFailed>
  <MessageScreenshotSavedAs>Captura de pantalla guardada como: {0}</MessageScreenshotSavedAs>
  <MessageNoLongerSocialFighting>{PAWN1_labelShort} y {PAWN2_labelShort} ya no están peleando.</MessageNoLongerSocialFighting>
  <MessageNoLongerBingingOnDrug>{2_labelShort} ya no está puesto(a) con {1}.</MessageNoLongerBingingOnDrug>
  <MessageNoLongerOnTargetedInsultingSpree>{PAWN_labelShort} ya no está lanzando insultos contra {TARGET_label}.</MessageNoLongerOnTargetedInsultingSpree>
  <MessageRottedAwayInStorage>{1_label} se ha podrido en el almacén.</MessageRottedAwayInStorage>
  <MessageFoodPoisoning>{PAWN_labelShort} se ha intoxicado con: {FOOD_labelShort}. Causa: {2}</MessageFoodPoisoning>
  <MessagePawnLostWhileFormingCaravan>{0} ha sido sacado de la caravana.</MessagePawnLostWhileFormingCaravan>
  <MessagePawnLostWhileFormingCaravan_AllLost>El proceso de formación de la caravana ha terminado.</MessagePawnLostWhileFormingCaravan_AllLost>
  <MessageCaravanFormationPaused>El proceso de formación de la caravana continuará cuando todos se recuperen de su colapso mental.</MessageCaravanFormationPaused>
  <MessageCaravanFormationUnpaused>Tus colonos continuarán ahora formando la caravana.</MessageCaravanFormationUnpaused>
  <MessageCaravanMemberHasExtremeMentalBreak>Uno de los miembros de la caravana ha tenido un colapso mental.</MessageCaravanMemberHasExtremeMentalBreak>
  <MessageMaxPlanetCoveragePerformanceWarning>Advertencia: Puede llevar mucho tiempo generar un planeta entero.</MessageMaxPlanetCoveragePerformanceWarning>
  <MessagePlantDiedOfCold>{0} ha muerto debido al frío.</MessagePlantDiedOfCold>
  <MessagePlantDiedOfRot_LeftUnharvested>{0} se ha podrido por no haber sido cosechada a tiempo.</MessagePlantDiedOfRot_LeftUnharvested>
  <MessagePlantDiedOfRot_ExposedToLight>{0} ha muerto por la falta de luz.</MessagePlantDiedOfRot_ExposedToLight>
  <MessagePlantDiedOfRot>{0} se ha podrido.</MessagePlantDiedOfRot>
  <MessagePlantDiedOfPoison>{0} ha muerto a causa de una toxina.</MessagePlantDiedOfPoison>
  <MessagePlantDiedOfBlight>{1_label} ha muerto debido a una plaga.</MessagePlantDiedOfBlight>
  <MessagePawnBeingBurned>¡{1_labelShort} se está quemando debido a la temperatura del aire!</MessagePawnBeingBurned>
  <MessageAccidentalOverdose>¡{INGESTER} ha sufrido una sobredosis mientras consumía {DRUG_labelShort}!</MessageAccidentalOverdose>
  <MessageCaravanArrivedAtDestination>{0} ha llegado a su destino.</MessageCaravanArrivedAtDestination>
  <MessagePawnLeftMapAndCreatedCaravan>{1_labelShort} ha dejado la zona con la caravana.</MessagePawnLeftMapAndCreatedCaravan>
  <MessagePawnLeftMapAndCreatedCaravan_AnimalsWantToJoin>Tus animales se están moviendo para unirse.</MessagePawnLeftMapAndCreatedCaravan_AnimalsWantToJoin>
  <MessageSettledInExistingMap>Te has asentado con éxito en una nueva zona.</MessageSettledInExistingMap>
  <MessagePermanentWoundHealed>El/la {2} de {PAWN_labelShort} ha sanado. Causa: {0}</MessagePermanentWoundHealed>
  <MessageRescueeDidntJoin>[PAWN_nameDef] se ha recuperado y ha decidido marcharse.</MessageRescueeDidntJoin>
  <MessageTransporterUnreachable>No se puede llegar hasta algunas de las cápsulas de transporte.</MessageTransporterUnreachable>
  <MessageTransportersNotAdjacent>Todos los lanza-cápsulas conectados a las cápsulas de transporte seleccionadas deben estar adyacentes entre sí.</MessageTransportersNotAdjacent>
  <MessageTransportersLoadCanceled_TransporterDestroyed>El proceso de carga se ha cancelado porque una de las cápsulas de transporte ha sido destruida.</MessageTransportersLoadCanceled_TransporterDestroyed>
  <MessageTransporterSingleLoadCanceled_TransporterDestroyed>El proceso de carga se ha cancelado porque la lanzadera ha sido destruida.</MessageTransporterSingleLoadCanceled_TransporterDestroyed>
  <MessageTransportersLoadCanceled_FuelingPortGiverDeSpawned>El proceso de carga se ha cancelado porque uno de los lanza-cápsulas ha sido destruido.</MessageTransportersLoadCanceled_FuelingPortGiverDeSpawned>
  <MessageTransportersLoadingProcessStarted>Ahora tus colonos cargarán los objetos seleccionados en las cápsulas de transporte.</MessageTransportersLoadingProcessStarted>
  <MessageTransporterSingleLoadingProcessStarted>Las personas y objetos seleccionados serán cargados en la lanzadera.</MessageTransporterSingleLoadingProcessStarted>
  <MessageTransportPodsArrived>Tus cápsulas de transporte han llegado.</MessageTransportPodsArrived>
  <MessageTransportPodsArrivedAndLost>Tus cápsulas de transporte han llegado, pero como no había ningun colono dentro, el contenido se ha perdido.</MessageTransportPodsArrivedAndLost>
  <MessageTransportPodsArrivedAndAddedToCaravan>Tus cápsulas de transporte han llegado. El contenido se ha añadido a {0}.</MessageTransportPodsArrivedAndAddedToCaravan>
  <MessageFinishedLoadingTransporters>Tus colonos han terminado de cargar las cápsulas de transporte.</MessageFinishedLoadingTransporters>
  <MessageFinishedLoadingTransporterSingle>La lanzadera se ha cargado con la mercancía requerida y está lista para despegar.</MessageFinishedLoadingTransporterSingle>
  <MessageCantLoadMoreIntoTransporters>Tu {1} no puede terminar de cargar las cápsulas de transporte porque algunos artículos o personas no están disponibles ({2_labelShort}).</MessageCantLoadMoreIntoTransporters>
  <MessageTransportPodsDestinationIsInvalid>El destino seleccionado no es válido.</MessageTransportPodsDestinationIsInvalid>
  <MessageTransportPodsDestinationIsTooFar>Cada lanza-cápsulas necesita por lo menos {0}x biocombustible para enviar las cápsulas a esa distancia.</MessageTransportPodsDestinationIsTooFar>
  <MessageReformedCaravan>La caravana se ha reformado.</MessageReformedCaravan>
  <MessageCantBanishLastColonist>No puedes desterrar al último colono.</MessageCantBanishLastColonist>
  <MessageCantEquipCustom>No puede equiparse: {0}.</MessageCantEquipCustom>
  <MessageCantEquipIncapableOfViolence>No puede equiparse: {1_labelShort} es incapaz de luchar.</MessageCantEquipIncapableOfViolence>
  <MessageCantEquipIncapableOfManipulation>No puede equiparse: incapaz.</MessageCantEquipIncapableOfManipulation>
  <MessageCantWearApparelMissingBodyParts>No puede equiparse: a {1_labelShort} le faltan partes corporales.</MessageCantWearApparelMissingBodyParts>
  <MessageCantUnequipLockedApparel>El colono se niega a quitarse esto.</MessageCantUnequipLockedApparel>
  <MessageWouldReplaceLockedApparel>No es posible: esto reemplazaría una vestimenta que {1_labelShort} se niega a quitarse.</MessageWouldReplaceLockedApparel>
  <MessageSlaughteringBondedAnimal>Debido a que comparten un vínculo, sacrificar a {DESIGNATED_labelShort} hará muy infeliz a {BONDED_labelShort}.</MessageSlaughteringBondedAnimal>
  <MessageReleaseBondedAnimal>Debido a que están vinculados, liberar a {DESIGNATED_labelShort} hará a {BONDED_labelShort} infeliz.</MessageReleaseBondedAnimal>
  <MessageCaravanRanOutOfFood>{0} se ha quedado sin comida ({PAWN_label}).</MessageCaravanRanOutOfFood>
  <MessageCaravanDeathCorpseAddedToInventory>El cadáver de {PAWN_definite} ha sido recogido por la caravana. Es pesado y puede llegar a impedir el movimiento de ésta, pero puede ser abandonado desde la pestaña de objetos de la caravana.</MessageCaravanDeathCorpseAddedToInventory>
  <MessageSelectOwnBaseToFormCaravan>Para formar una caravana, selecciona tu propia colonia o algún otro lugar donde tengas personas.</MessageSelectOwnBaseToFormCaravan>
  <MessageScreenResTooSmallForUIScale>Con esta resolución y escala de UI, la interface del juego no cabría en la pantalla. Por favor reduce la escala de UI o aumenta la resolución.</MessageScreenResTooSmallForUIScale>
  <MessageYouHaveToReformCaravanNow>Debes reformar la caravana ahora. Todo el que se quede será abandonado.</MessageYouHaveToReformCaravanNow>
  <MessageDefendersAttacking>Los {0} de {1} estan atacando tu {2}.</MessageDefendersAttacking>
  <MessageMechanoidsAssembled>Los mecanoides han sido ensamblados y te están atacando.</MessageMechanoidsAssembled>
  <MessageMechanoidsLeftToAssemble>Mecanoides que quedan por ser ensamblados</MessageMechanoidsLeftToAssemble>
  <MessageMechanoidsReinforcementsDrop>La baliza mecanoide ha desplegado refuerzos en cápsulas de desembarco cercanas.</MessageMechanoidsReinforcementsDrop>
  <MessageSelfTendUnsatisfied>Para poder auto-atenderse, {1_labelShort} debe primero ser asignado al trabajo de Médico.</MessageSelfTendUnsatisfied>
  <MessageCannotSelfTendEver>{1_labelShort} es incapaz de trabajar como Médico, y por tanto no puede auto-atenderse.</MessageCannotSelfTendEver>
  <MessageCantAddWaypointBecauseImpassable>Esta casilla es intransitable..</MessageCantAddWaypointBecauseImpassable>
  <MessageCantAddWaypointBecauseUnreachable>No es posible alcanzar esta casilla desde la última parada.</MessageCantAddWaypointBecauseUnreachable>
  <MessageCantAddWaypointBecauseLimit>No puedes añadir más de {0} paradas.</MessageCantAddWaypointBecauseLimit>
  <MessageCantRemoveWaypointBecauseFirst>No puedes eliminar esta parada.</MessageCantRemoveWaypointBecauseFirst>
  <MessageCantDoExecutionBecauseNoWardenCapableOfViolence>Ninguno de tus guardias es capaz de realizar actos violentos. La ejecución no se llevará a cabo.</MessageCantDoExecutionBecauseNoWardenCapableOfViolence>
  <MessageCanReformCaravanNowNoMoreEnemies>Ahora el área es segura. Puedes reformar la caravana en el mapa del mundo.</MessageCanReformCaravanNowNoMoreEnemies>
  <MessageCanReformCaravanNowNoMoreEnemiesButUnexploredAreas>Ahora el área es segura, pero hay algunas habitaciones sin explorar. Puedes seguir explorando o reformar la caravana en el mapa del mundo.</MessageCanReformCaravanNowNoMoreEnemiesButUnexploredAreas>
  <MessageCantBanishDownedPawn>No puedes desterrar a {1_labelShort} ya que no puede caminar.</MessageCantBanishDownedPawn>
  <MessageSleepingPawnsWokenUp>{0} se han despertado.</MessageSleepingPawnsWokenUp>
  <MessageMechClusterDefeated>Las construcciones del grupo mecanoide han sido derrotadas.</MessageMechClusterDefeated>
  <MessageCompSpawnerSpawnedItem>Objeto producido: {0}.</MessageCompSpawnerSpawnedItem>
  <MessageHediffCuredByItem>Enfermedad curada: {0}.</MessageHediffCuredByItem>
  <MessageBodyPartCuredByItem>Parte del cuerpo restaurada: {0}.</MessageBodyPartCuredByItem>
  <MessageResearchProjectFinishedByItem>Tecnología proporcionada: {0}.</MessageResearchProjectFinishedByItem>
  <MessagePawnResurrected>¡{0} ha vuelto a la vida!</MessagePawnResurrected>
  <MessageFailedToRescueRelative>Has fallado en el rescate de {PAWN_labelShort}. Esto hará que {RELATIVE_labelShort} se sienta triste.</MessageFailedToRescueRelative>
  <MessageRescuedRelative>Has rescatado a {PAWN_labelShort}. Esto hará que {RELATIVE_labelShort} se sienta feliz.</MessageRescuedRelative>
  <MessageTornadoLeftMap>El tornado ha dejado la zona.</MessageTornadoLeftMap>
  <MessageTornadoDissipated>El tornado se ha disipado.</MessageTornadoDissipated>
  <MessagePeaceTalksNoDiplomat>No hay ningún diplomático competente y consciente.</MessagePeaceTalksNoDiplomat>
  <MessageWarningCavePlantsExposedToLight>Advertencia: {0} no puede vivir cuando se expone a la luz.</MessageWarningCavePlantsExposedToLight>
  <MessageTargetedTantrumChangedTarget>{PAWN_labelShort} no pudo alcanzar a {OLDTARGET_label} así que decidió redirigir su ira hacia {TARGET_label}.</MessageTargetedTantrumChangedTarget>
  <MessageTargetedInsultingSpreeChangedTarget>{PAWN_labelShort} no pudo alcanzar a {OLDTARGET_label} así que decidió redirigir sus insultos hacia {TARGET_label}.</MessageTargetedInsultingSpreeChangedTarget>
  <MessageMurderousRageChangedTarget>{PAWN_labelShort} ha decidido redirigir su ira hacia {TARGET_label}.</MessageMurderousRageChangedTarget>
  <MessagePlantIncompatibleWithRoof>{0} no puede crecer bajo techo.</MessagePlantIncompatibleWithRoof>
  <MessageRoofIncompatibleWithPlant>No se puede construir un techo sobre {0}.</MessageRoofIncompatibleWithPlant>
  <MessagePlayerTriedToLeaveMapViaExitGrid_CanReform>Para salir de la zona, utiliza el botón 'reformar caravana' en la vista del mundo.</MessagePlayerTriedToLeaveMapViaExitGrid_CanReform>
  <MessagePlayerTriedToLeaveMapViaExitGrid_CantReform>No puedes dejar el mapa ahora.</MessagePlayerTriedToLeaveMapViaExitGrid_CantReform>
  <MessageGoodwillChanged>Las relaciones con {0} han cambiado de {1} a {2}.</MessageGoodwillChanged>
  <MessageGoodwillChangedWithReason>Las relaciones con {0} han cambiado de {1} a {2} ({3}).</MessageGoodwillChangedWithReason>
  <GoodwillChangedReason_AttackedPawn>se atacó a {1_labelShort}</GoodwillChangedReason_AttackedPawn>
  <GoodwillChangedReason_UsedItem>se usó {ITEM_labelShort} en {TARGET_labelShort}</GoodwillChangedReason_UsedItem>
  <GoodwillChangedReason_UsedAbility>se usó {0} en {1}</GoodwillChangedReason_UsedAbility>
  <GoodwillChangedReason_RemovedBodyPart>se amputó {0}</GoodwillChangedReason_RemovedBodyPart>
  <GoodwillChangedReason_RemovedImplant>se extrajo {0}</GoodwillChangedReason_RemovedImplant>
  <GoodwillChangedReason_DowngradedImplant>se degradó {0}</GoodwillChangedReason_DowngradedImplant>
  <GoodwillChangedReason_NeedlesslyInstalledWorseBodyPart>se instaló {0} sin necesidad</GoodwillChangedReason_NeedlesslyInstalledWorseBodyPart>
  <GoodwillChangedReason_CapturedPawn>se capturó a {1_labelShort}</GoodwillChangedReason_CapturedPawn>
  <GoodwillChangedReason_PawnCrushed>se aplastó a {1_labelShort}</GoodwillChangedReason_PawnCrushed>
  <GoodwillChangedReason_PawnDied>{1_labelShort} murió</GoodwillChangedReason_PawnDied>
  <GoodwillChangedReason_PawnStripped>{0_labelShort} fue desnudado(a)</GoodwillChangedReason_PawnStripped>
  <GoodwillChangedReason_Traded>se comerció</GoodwillChangedReason_Traded>
  <GoodwillChangedReason_AttackedCaravan>se atacó una caravana</GoodwillChangedReason_AttackedCaravan>
  <GoodwillChangedReason_ExitedMapHealthy>{1_labelShort} salió sano y salvo del mapa</GoodwillChangedReason_ExitedMapHealthy>
  <GoodwillChangedReason_Tended>se atendió a {1_labelShort}</GoodwillChangedReason_Tended>
  <GoodwillChangedReason_ReceivedGift>se recibió un regalo</GoodwillChangedReason_ReceivedGift>
  <GoodwillChangedReason_FulfilledTradeRequest>se cumplió con una oferta comercial</GoodwillChangedReason_FulfilledTradeRequest>
  <GoodwillChangedReason_FinishedQuest>se completó una misión</GoodwillChangedReason_FinishedQuest>
  <GoodwillChangedReason_UsedForbiddenThing>{PAWN_labelShort} usó {CULPRIT}</GoodwillChangedReason_UsedForbiddenThing>
  <GoodwillChangedReason_SoldPawn>se vendió {0_labelShort}</GoodwillChangedReason_SoldPawn>
  <GoodwillChangedReason_EuthanizedPawn>se practicó eutanasia a {PAWN_labelShort}</GoodwillChangedReason_EuthanizedPawn>
  <GoodwillChangedReason_RequestedMilitaryAid>se solicitó ayuda militar</GoodwillChangedReason_RequestedMilitaryAid>
  <GoodwillChangedReason_RequestedTrader>se solicitó una caravana de comercio</GoodwillChangedReason_RequestedTrader>
  <GoodwillChangedReason_CausedNeuroquakeEcho>se ha provocado una avalancha psíquica</GoodwillChangedReason_CausedNeuroquakeEcho>
  <GoodwillChangedReason_CausedBerserk>se ha inducido 'frenesí' en {PAWN_labelShort}</GoodwillChangedReason_CausedBerserk>
  <GoodwillChangeReason_AttackedFaction>se ha atacado a {0_name}</GoodwillChangeReason_AttackedFaction>
  <GoodwillChangeReason_ShuttleDestroyed>se ha destruido la lanzadera</GoodwillChangeReason_ShuttleDestroyed>
  <GoodwillChangeReason_CiviliansLost>pérdida civil</GoodwillChangeReason_CiviliansLost>
  <GoodwillChangeReason_CommanderLost>pérdida del comandante</GoodwillChangeReason_CommanderLost>
  <MessageGiftGivenButNotAppreciated>{0} aceptan tu regalo pero no lo aprecian.</MessageGiftGivenButNotAppreciated>
  <MessageCantGiveGiftBecauseCantCarryEncumbered>La caravana está al máximo y no puede llevar nada más.</MessageCantGiveGiftBecauseCantCarryEncumbered>
  <MessageCantGiveGiftBecauseCantCarry>La caravana no puede con tanto. Los regalos pesan {0} pero la caravana sólo puede llevar {1} más.</MessageCantGiveGiftBecauseCantCarry>
  <MessageFormedCaravan>{0} se ha formado y ahora está viajando por el mapa del mundo.</MessageFormedCaravan>
  <MessageFormedCaravan_Orders>Órdenes</MessageFormedCaravan_Orders>
  <MessageBillValidationStoreZoneDeleted>El "{0}" de {1} ya no puede dejarse en las reservas eliminadas {2}.</MessageBillValidationStoreZoneDeleted>
  <MessageBillValidationStoreZoneUnavailable>El "{0}" de {1} ya no puede dejarse en reservas deshabilitadas {2}.</MessageBillValidationStoreZoneUnavailable>
  <MessageBillValidationPawnUnavailable>{0} ya no puede trabajar en "{1}" a {2}. Se ha eliminado la restricción.</MessageBillValidationPawnUnavailable>
  <MessageBillValidationIncludeZoneDeleted>El "{0}" de {1} ya no puede contar los artículos de las reservas eliminadas {2}.</MessageBillValidationIncludeZoneDeleted>
  <MessageBillValidationIncludeZoneUnavailable>El "{0}" de {1} ya no puede contar los artículos de la reserva deshabilitada {2}.</MessageBillValidationIncludeZoneUnavailable>
  <MessageBillValidationStoreZoneInsufficient>El "{0}" de {1} ya no pueden dejarse todos los productos en la reserva {2}.</MessageBillValidationStoreZoneInsufficient>
  <MessageAnimalReturnedWild>Debido a la falta de manutención, {1_labelShort} ha regresado a su hábitat natural.</MessageAnimalReturnedWild>
  <MessageAnimalReturnedWildReleased>{1_labelShort} ha sido liberado de vuelta a la naturaleza.</MessageAnimalReturnedWildReleased>
  <MessageAnimalLostSkill>Debido a la falta de adiestramiento, {ANIMAL_labelShort} ha perdido una habilidad: {1}</MessageAnimalLostSkill>
  <MessageTranslationReportSaved>Informe de traducción guardado en {0}</MessageTranslationReportSaved>
  <MessageCaravanArrivalActionNoLongerValid>{0} no pudo llegar a su destino.</MessageCaravanArrivalActionNoLongerValid>
  <MessageEnterCooldownBlocksEntering>No puede volver durante los próximos {0} días.</MessageEnterCooldownBlocksEntering>
  <MessagePermitCooldownFinished>{0_labelShort} puede utilizar ahora "{1}" libremente.</MessagePermitCooldownFinished>
  <MessagePredatorHuntingPlayerAnimal>¡{PREDATOR} está cazando a {PREY_definite} para alimentarse!</MessagePredatorHuntingPlayerAnimal>
  <MessagePrisonerResistanceBroken>La resistencia del prisionero {PRISONER_labelShort} ha sido suprimida por {WARDEN_labelShort}.</MessagePrisonerResistanceBroken>
  <MessagePrisonerResistanceBroken_RecruitAttempsWillBegin>Los intentos de reclutamiento empezarán.</MessagePrisonerResistanceBroken_RecruitAttempsWillBegin>
  <MessageModWithPackageIdAlreadyEnabled>Otro mod con la ID {0} ya está activo. Desactiva {1} antes de intentar activar este otro.</MessageModWithPackageIdAlreadyEnabled>
  <MessageDisableModsBeforeCleaningTranslationFiles>Desactiva todos los mods antes de usar esta herramienta.</MessageDisableModsBeforeCleaningTranslationFiles>
  <MessageUnpackBeforeCleaningTranslationFiles>Desempaqueta y después elimina todos los archivos comprimidos de traducción de este idioma antes de usar esta herramienta.</MessageUnpackBeforeCleaningTranslationFiles>
  <MessageTranslationFilesCleanupDone>Listo. Carpeta afectada: {0}</MessageTranslationFilesCleanupDone>
  <MessageCantCleanupTranslationFilesBeucaseOfXmlError>Uno de los archivos de traducción ({0}) no pudo ser cargado. Todos los errores de análisis de XML deben ser resueltos primero.</MessageCantCleanupTranslationFilesBeucaseOfXmlError>
  <MessageCapturingWillAngerFaction>Advertencia: Capturar a {PAWN_nameDef} enfadará a la facción {PAWN_factionName}.</MessageCapturingWillAngerFaction>
  <MessageStrippingWillAngerFaction>Advertencia: Desnudar a {PAWN_nameDef} enfadará a {PAWN_factionName}.</MessageStrippingWillAngerFaction>
  <MessageCantShootInMelee>No puede disparar en combate cuerpo a cuerpo.</MessageCantShootInMelee>
  <MessageNoColonistCanAcceptQuest>Ninguno de tus {0} puede aceptar esta misión ahora mismo.</MessageNoColonistCanAcceptQuest>
  <MessageCannotAcceptQuest>No se puede aceptar esta misión.</MessageCannotAcceptQuest>
  <MessageQuestAccepted>{0_definite} ha aceptado una misión: {1}</MessageQuestAccepted>
  <MessagePawnLeaving>{0} se va.</MessagePawnLeaving>
  <MessagePawnsLeaving>{0} se van.</MessagePawnsLeaving>
  <MessageMonumentDestroyedBecauseOfDisallowedBuilding>El monumento ha sido destruido porque has construido en su interior algo que no estaba permitido.</MessageMonumentDestroyedBecauseOfDisallowedBuilding>
  <MessageNoResearchBenchForTechprint>No aplicable: no hay ninguna mesa de investigación libre y accesible.</MessageNoResearchBenchForTechprint>
  <NoValidDestinationFound>No se ha encontrado un destino válido para {0}</NoValidDestinationFound>
  <MessageMinifiedTreeDied>Acaba de morir un árbol extraído.</MessageMinifiedTreeDied>
  <MessageResearchMenuWithoutBench>Advertencia: la Investigación no empezará hasta que construyas una mesa de investigación.</MessageResearchMenuWithoutBench>
  <MessageActivatorProximityTriggered>{0_indefinite} ha accionado un activador de proximidad.</MessageActivatorProximityTriggered>
  <MessageCannotSelectInvisibleStat>{0_label} está escondido.</MessageCannotSelectInvisibleStat>
  <MessagePrisonerCannotEquipWeapon>{PAWN_nameDef} es un prisionero</MessagePrisonerCannotEquipWeapon>
  <MessageBedLostAssignment>{0} ya no está asignado a {1_nameDef}.</MessageBedLostAssignment>
  <MessageBedDestroyed>{0} asignado a {1_nameDef} fue destruído.</MessageBedDestroyed>
  <Spectate>presenciar</Spectate>
  <AssignToRole>Asignar a {0}</AssignToRole>
  <RitualBegun>{0} ha empezado.</RitualBegun>
  <MaxPawnsPerRole>El número máximo de {0} es {1}.</MaxPawnsPerRole>
  <RoleIsLocked>El rol de {0} está bloqueado.</RoleIsLocked>
  <MessageRitualNeedsAtLeastOnePerson>Necesitas al menos un participante.</MessageRitualNeedsAtLeastOnePerson>
  <MessageRitualNeedsAtLeastOneSpectator>Necesitas al menos un testigo.</MessageRitualNeedsAtLeastOneSpectator>
  <MessageRitualNeedsAtLeastOneRolePawn>Necesitas un {0}.</MessageRitualNeedsAtLeastOneRolePawn>
  <MessageRitualNeedsAtLeastNumRolePawn>Necesitas al menos {1} {0}.</MessageRitualNeedsAtLeastNumRolePawn>
  <MessageRitualPawnDowned>{0_labelShort} fue derribado.</MessageRitualPawnDowned>
  <MessageRitualPawnPrisonerNotSecured>{0_labelShort} está escapando.</MessageRitualPawnPrisonerNotSecured>
  <MessageRitualPawnSlaveNotSecured>{0_labelShort} se está rebelando.</MessageRitualPawnSlaveNotSecured>
  <MessageRitualPawnReleased>{0_labelShort} se está liberando.</MessageRitualPawnReleased>
  <MessageRitualPawnInjured>{0_labelShort} está herido.</MessageRitualPawnInjured>
  <MessageRitualRoleRequired>{0_labelShort} debe tener uno de estos roles</MessageRitualRoleRequired>
  <MessageRitualRoleMustBePrisoner>{0} debe ser un prisionero.</MessageRitualRoleMustBePrisoner>
  <MessageRitualRoleMustBeAnimal>{0} debe ser un animal.</MessageRitualRoleMustBeAnimal>
  <MessageRitualRoleMustBeHumanlike>{0} debe ser un humano.</MessageRitualRoleMustBeHumanlike>
  <MessageRitualNoRolesAvailable>No hay roles disponibles para {0_labelShort}.</MessageRitualNoRolesAvailable>
  <MessageRitualNotOfPlayerIdeo>{0_labelShort} no es miembro de la ideoligión de ninguna colonia.</MessageRitualNotOfPlayerIdeo>
  <MessageRitualRoleMustHaveEyes>{0} debe tener ojos</MessageRitualRoleMustHaveEyes>
  <MessageRitualRoleMustRequireScarification>{0_labelShort} no requiere más escarificación.</MessageRitualRoleMustRequireScarification>
  <MessageRitualRoleMustBePrisonerOrSlave>{0} debe ser un prisionero o esclavo.</MessageRitualRoleMustBePrisonerOrSlave>
  <MessageRitualRoleMustBeCapableOfFighting>{0_labelShort} debe ser capaz de luchar.</MessageRitualRoleMustBeCapableOfFighting>
  <MessageRitualRoleCannotReplaceRequiredPawn>este rol no puede ser llevado a cabo por otra persona.</MessageRitualRoleCannotReplaceRequiredPawn>
  <MessageRitualRolePawnRecentlyTornConnection>{0_labelShort} no puede conectarse a un Árbol Gauranlen debido a que una conexión {0_possessive} fue desgarrada recientemente.</MessageRitualRolePawnRecentlyTornConnection>
  <MessageRitualRolePawnHasSameIdeo>{0_labelShort} tiene la misma ideoligión que el conversor.</MessageRitualRolePawnHasSameIdeo>
  <MessageRitualRoleMustBeCapableOfWardening>{0_labelShort} debe ser capaz de deambular.</MessageRitualRoleMustBeCapableOfWardening>
  <MessageRitualRoleMustBeCapableOfGeneric>{0} debe ser capaz de {1}.</MessageRitualRoleMustBeCapableOfGeneric>
  <MessageRitualRoleMustNotBePrisonerToSpectate>los prisioneros no pueden {0}.</MessageRitualRoleMustNotBePrisonerToSpectate>
  <MessageRitualRoleMustHaveIdeoToSpectate>solo {0} puede {1}.</MessageRitualRoleMustHaveIdeoToSpectate>
  <MessageRitualRoleMustHaveIdeoToDoRole>solo {0} puede ocupar el rol de {1}.</MessageRitualRoleMustHaveIdeoToDoRole>
  <MessageRitualRoleMustBeColonist>debe ser colono para ser el rol {0}.</MessageRitualRoleMustBeColonist>
  <MessageRitualRoleMustHaveLargerBodySize>{0} debe tener un animal con un tamaño de cuerpo mínimo de {1}</MessageRitualRoleMustHaveLargerBodySize>
  <MessageRitualPawnMentalState>{0_labelShort} sufre un estado mental.</MessageRitualPawnMentalState>
  <MessageRitualPawnIsAlreadyBelievingIdeo>{0_labelShort} ya está {1}.</MessageRitualPawnIsAlreadyBelievingIdeo>
  <MessageRitualCannotAssignAnyRoleFromSpectating>{0_labelShort} solo puede ser testigo.</MessageRitualCannotAssignAnyRoleFromSpectating>
  <MessageRitualRoleMustNotBeImprisonedWildMan>{0} no puede ser un hombre/mujer salvaje encarcelado.</MessageRitualRoleMustNotBeImprisonedWildMan>
  <MessageRitualRoleMustNotBeImprisoned>{0} debe ser puesto en libertad.</MessageRitualRoleMustNotBeImprisoned>
  <MessagePlayerMustSelectTile>Debes seleccionar un espacio para continuar.</MessagePlayerMustSelectTile>
  <CannotPlantThing>No se puede plantar {0_labelShort}</CannotPlantThing>
  <MessageWarningNotEnoughFertility>Se necesita más terreno fértil.</MessageWarningNotEnoughFertility>
  <BlockedBy>bloqueado por {0_label}.</BlockedBy>
  <AdjacentSowBlocker>No puede ser plantado al lado de {0_label}.</AdjacentSowBlocker>
  <TooCloseToOtherPlant>Demasiado cerca de {0_label}.</TooCloseToOtherPlant>
  <TooCloseToOtherSeedPlantCell>Demasiado cerca a la plantación de {0}.</TooCloseToOtherSeedPlantCell>
  <MessageWarningCutImportantPlant>Advertencia: {0} se ha marcado para cortar.</MessageWarningCutImportantPlant>
  <MessageNuzzledPawnGaveNameTo>{NAMER_nameFull} ha nombrado a {1}, {NAMEE_nameFull}, al haber recibido una dulce caricia.</MessageNuzzledPawnGaveNameTo>
  <MessageSiteCountdownBecauseNoMoreEnemies>Has vencido a todos los enemigos. En {0}, la caravana será reformada automáticamente.</MessageSiteCountdownBecauseNoMoreEnemies>
  <MessageSiteCountdownBecauseNoEnemiesInitially>En {0}, la caravana será reformada automáticamente. Puedes reformar la caravana ahora desde la pantalla del Mundo.</MessageSiteCountdownBecauseNoEnemiesInitially>
  <GoodwillChangedReason_NaturallyOverTime>tendencia natural a alcanzar {0} con el tiempo</GoodwillChangedReason_NaturallyOverTime>
  
</LanguageData>